setup.py
pylogeny/JSONWriter.py
pylogeny/__init__.py
pylogeny/__version__.py
pylogeny/alignment.py
pylogeny/base.py
pylogeny/database.py
pylogeny/executable.py
pylogeny/fitch.cpp
pylogeny/fitch.so
pylogeny/heuristic.py
pylogeny/landscape.py
pylogeny/landscapeWriter.py
pylogeny/libpllWrapper.c
pylogeny/model.py
pylogeny/newick.py
pylogeny/parsimony.py
pylogeny/pll.py
pylogeny/rearrangement.py
pylogeny/scoring.py
pylogeny/tree.py
pylogeny.egg-info/PKG-INFO
pylogeny.egg-info/SOURCES.txt
pylogeny.egg-info/dependency_links.txt
pylogeny.egg-info/not-zip-safe
pylogeny.egg-info/requires.txt
pylogeny.egg-info/top_level.txt