Metadata-Version: 1.0
Name: pylogeny
Version: 0.3.6.9
Summary: A code framework for phylogenetic tree reconstruction, rearrangement, scoring, and for the manipulation, heuristic search, and analysis of the phylogenetic tree combinatorial space.
Home-page: http://www.github.com/AlexSafatli/Pylogeny
Author: Alex Safatli
Author-email: safatli@cs.dal.ca
License: MIT
Platform: UNKNOWN
